directree/__init__.py
directree/main.py
directree-0.9.dist-info/METADATA
directree-0.9.dist-info/WHEEL
directree-0.9.dist-info/entry_points.txt
directree-0.9.dist-info/top_level.txt
directree-0.9.dist-info/RECORD
