Metadata-Version: 2.1
Name: directree
Version: 0.9
Summary: A CLI tool to generate a customizable directory tree while ignoring specified files and folders.
Classifier: Programming Language :: Python :: 3
Classifier: Programming Language :: Python :: 3.6
Classifier: Programming Language :: Python :: 3.7
Classifier: Programming Language :: Python :: 3.8
Classifier: Programming Language :: Python :: 3.9
Classifier: Operating System :: OS Independent
Requires-Python: >=3.6
